<abilitymods>
  <zpspcqueenanne>
    <ability>PowerBroadside<rof>60</rof></ability>
    <ability>PowerGreekFire<rof>60</rof></ability>
  </zpspcqueenanne>
  <zpspcblackpearl>
    <ability>PowerBroadside<rof>60</rof></ability>
  </zpspcblackpearl>
  <zpspcneptunegalley>
    <ability>PowerBroadside<rof>60</rof></ability>
    <ability>PowerLongRange<rof>60</rof></ability>
  </zpspcneptunegalley>
  <zpmalteseriggedship>
    <ability>PowerBroadside<rof>60</rof></ability>
  </zpmalteseriggedship>
  <zpspclineship>
    <ability>PowerBroadside<rof>60</rof></ability>
  </zpspclineship>
  <zpmaltesegun>
    <ability>dePowerMalteseGunLongRangeAttack<tech>Industrialize</tech><rof>60</rof></ability>
  </zpmaltesegun>
  <zpspctreasureship>
    <ability>PowerLongRange<rof>60</rof></ability>
    <ability>PowerBroadside<rof>60</rof></ability>
  </zpspctreasureship>
  <zpwokousteamer>
    <ability>deFullSteam<rof>90</rof><donotforcestop>true</donotforcestop><castonself>true</castonself><activetimecooldown>true</activetimecooldown></ability>
  </zpwokousteamer>
  <zpwokoufuchuan>
    <ability>PowerBroadside<rof>60</rof></ability>
  </zpwokoufuchuan>
  <zpirontank>
    <ability>dePowerRoundelExplodeAttack<tech>zpIronTanks</tech><rof>10</rof><castonself>true</castonself></ability>
    <ability>dePowerRoundelCascadeAttack<tech>zpIronTanks</tech><rof>10</rof><castonself>true</castonself></ability>
  </zpirontank>
  <zpirontankproxy>
    <ability>dePowerRoundelExplodeAttack<rof>10</rof><castonself>true</castonself></ability>
    <ability>dePowerRoundelCascadeAttack<rof>10</rof><castonself>true</castonself></ability>
  </zpirontankproxy>
  <zpairship>
    <ability>zpAirshipLighthouse<rof>60</rof><castonself>true</castonself></ability>
    <ability>zpPowerFireBomb<tech>zpBattleAirship</tech><rof>30</rof></ability>
    <ability>zpMustardGas<tech>zpMustardGas</tech><rof>30</rof></ability>
  </zpairship>
  <zpsubmarine>
    <ability>zpPowerShunt<allowwhilestealthed>true</allowwhilestealthed><rof>60</rof></ability>
  </zpsubmarine>
  <zpnautilus>
    <ability>zpPowerShunt<allowwhilestealthed>true</allowwhilestealthed><rof>60</rof></ability>
  </zpnautilus>
  <zpairshipai>
    <ability>zpAirshipLighthouse<rof>60</rof><castonself>true</castonself></ability>
    <ability>zpPowerFireBomb<tech>zpBattleAirship</tech><rof>60</rof></ability>
    <ability>zpMustardGas<tech>zpMustardGas</tech><rof>60</rof></ability>
  </zpairshipai>
  <zpNatConquistadorMusketeer>
		<ability>dePromotionHpROF
			<alwaysdisabledingrid>true</alwaysdisabledingrid>
			<forceshowrollover>true</forceshowrollover>
		</ability>
	</zpNatConquistadorMusketeer>
  <zppriest>
    <ability>PowerConvert<rof>60</rof></ability>
  </zppriest>
  <zpsaofeng>
    <ability>ypPowerHeavenlyFireBomb<rof>120</rof></ability>
    <ability>ypPowerCriticalAttack<alwaysdisabledingrid>true</alwaysdisabledingrid></ability>
  </zpsaofeng>
</abilitymods>